webob/__init__.py
webob/acceptparse.py
webob/byterange.py
webob/cachecontrol.py
webob/client.py
webob/compat.py
webob/cookies.py
webob/datetime_utils.py
webob/dec.py
webob/descriptors.py
webob/etag.py
webob/exc.py
webob/headers.py
webob/multidict.py
webob/request.py
webob/response.py
webob/static.py
webob/util.py
WebOb-1.8.8.dist-info/METADATA
WebOb-1.8.8.dist-info/WHEEL
WebOb-1.8.8.dist-info/license.txt
WebOb-1.8.8.dist-info/top_level.txt
WebOb-1.8.8.dist-info/zip-safe
WebOb-1.8.8.dist-info/RECORD
