Metadata-Version: 2.1
Name: WebOb
Version: 1.8.8
Summary: WSGI request and response object
Home-page: http://webob.org/
Author: Ian Bicking
Author-email: ianb@colorstudy.com
Maintainer: Pylons Project
License: MIT
Keywords: wsgi request web http
Classifier: Development Status :: 6 - Mature
Classifier: Intended Audience :: Developers
Classifier: License :: OSI Approved :: MIT License
Classifier: Topic :: Internet :: WWW/HTTP :: WSGI
Classifier: Topic :: Internet :: WWW/HTTP :: WSGI :: Application
Classifier: Topic :: Internet :: WWW/HTTP :: WSGI :: Middleware
Classifier: Programming Language :: Python :: 2.7
Classifier: Programming Language :: Python :: 3.4
Classifier: Programming Language :: Python :: 3.5
Classifier: Programming Language :: Python :: 3.6
Classifier: Programming Language :: Python :: 3.7
Classifier: Programming Language :: Python :: Implementation :: CPython
Classifier: Programming Language :: Python :: Implementation :: PyPy
Requires-Python: >=2.7,!=3.0.*,!=3.1.*,!=3.2.*
License-File: docs/license.txt
Provides-Extra: testing
Requires-Dist: pytest>=3.1.0; extra == "testing"
Requires-Dist: coverage; extra == "testing"
Requires-Dist: pytest-cov; extra == "testing"
Requires-Dist: pytest-xdist; extra == "testing"
Provides-Extra: docs
Requires-Dist: Sphinx>=1.7.5; extra == "docs"
Requires-Dist: pylons-sphinx-themes; extra == "docs"
